pymbo/__init__.py
pymbo/__main__.py
pymbo/cli.py
pymbo/launcher.py
pymbo/core/__init__.py
pymbo/core/algorithm_verifier.py
pymbo/core/batch_prediction_optimizer.py
pymbo/core/benchmark_algorithms.py
pymbo/core/blas_optimizer.py
pymbo/core/controller.py
pymbo/core/convergence_detector.py
pymbo/core/device_manager.py
pymbo/core/efficient_data_manager.py
pymbo/core/enhanced_benchmark_algorithms.py
pymbo/core/enhanced_optimizer.py
pymbo/core/fast_benchmark_algorithms.py
pymbo/core/gpu_benchmark_algorithms.py
pymbo/core/hypervolume_calculator.py
pymbo/core/hypervolume_calculator_original.py
pymbo/core/modern_acquisition_core.py
pymbo/core/optimizer.py
pymbo/core/orchestrator.py
pymbo/core/parallel_benchmark_algorithms.py
pymbo/core/parallel_whatif_simulation.py
pymbo/core/plot_data_fixer.py
pymbo/core/robust_mobo.py
pymbo/core/test_function_manager.py
pymbo/core/test_functions.py
pymbo/core/unified_benchmark_algorithms.py
pymbo/core/validation_engine.py
pymbo/core/whatif_simulation.py
pymbo/gui/__init__.py
pymbo/gui/algorithm_verification_widget.py
pymbo/gui/compact_controls.py
pymbo/gui/convergence_controls.py
pymbo/gui/goal_impact_dashboard.py
pymbo/gui/gp_slice_controls.py
pymbo/gui/gpu_acceleration_widget.py
pymbo/gui/gui.py
pymbo/gui/import_wizard.py
pymbo/gui/interactive_screening_window.py
pymbo/gui/model_diagnostics_controls.py
pymbo/gui/movable_controls.py
pymbo/gui/optimization_convergence_controls.py
pymbo/gui/parallel_coordinates_controls.py
pymbo/gui/parallel_optimization_controls.py
pymbo/gui/pareto_controls.py
pymbo/gui/plot_controls.py
pymbo/gui/progress_controls.py
pymbo/gui/response_importance_dialog.py
pymbo/gui/screening_execution_window.py
pymbo/gui/sensitivity_analysis_controls.py
pymbo/gui/surface_3d_controls.py
pymbo/gui/uncertainty_analysis_controls.py
pymbo/gui/unified_plot_controls.py
pymbo/gui/window_controls.py
pymbo/screening/README.md
pymbo/screening/__init__.py
pymbo/screening/design_space_generator.py
pymbo/screening/parameter_handler.py
pymbo-3.7.0.dist-info/licenses/LICENSE
pymbo-3.7.0.dist-info/METADATA
pymbo-3.7.0.dist-info/WHEEL
pymbo-3.7.0.dist-info/entry_points.txt
pymbo-3.7.0.dist-info/top_level.txt
pymbo-3.7.0.dist-info/RECORD
