Metadata-Version: 2.4
Name: pymbo
Version: 3.7.0
Summary: Python Multi-objective Bayesian Optimization framework
Home-page: https://pypi.org/project/pymbo/
Author: Jakub Jagielski
Author-email: Jakub Jagielski <jakubjagielski93@gmail.com>
License: MIT
Project-URL: Homepage, https://pypi.org/project/pymbo/
Project-URL: Bug Reports, https://github.com/jakub-jagielski/pymbo/issues
Project-URL: Source, https://github.com/jakub-jagielski/pymbo
Project-URL: Documentation, https://github.com/jakub-jagielski/pymbo#readme
Keywords: bayesian-optimization,multi-objective,optimization,machine-learning
Classifier: Development Status :: 4 - Beta
Classifier: Intended Audience :: Science/Research
Classifier: License :: OSI Approved :: MIT License
Classifier: Programming Language :: Python :: 3
Classifier: Programming Language :: Python :: 3.8
Classifier: Programming Language :: Python :: 3.9
Classifier: Programming Language :: Python :: 3.10
Classifier: Programming Language :: Python :: 3.11
Classifier: Programming Language :: Python :: 3.12
Classifier: Topic :: Scientific/Engineering :: Artificial Intelligence
Classifier: Topic :: Scientific/Engineering :: Mathematics
Classifier: Topic :: Software Development :: Libraries :: Python Modules
Classifier: Operating System :: OS Independent
Requires-Python: >=3.8
License-File: LICENSE
Requires-Dist: torch>=1.12.0
Requires-Dist: botorch>=0.8.0
Requires-Dist: gpytorch>=1.9.0
Requires-Dist: numpy>=1.21.0
Requires-Dist: pandas>=1.4.0
Requires-Dist: scipy>=1.8.0
Requires-Dist: scikit-learn>=1.1.0
Requires-Dist: matplotlib>=3.5.0
Requires-Dist: seaborn>=0.11.0
Requires-Dist: openpyxl>=3.0.0
Requires-Dist: xlsxwriter>=3.0.0
Requires-Dist: Pillow>=9.0.0
Provides-Extra: dev
Requires-Dist: pytest>=7.0.0; extra == "dev"
Requires-Dist: pytest-cov>=4.0.0; extra == "dev"
Requires-Dist: black>=22.0.0; extra == "dev"
Requires-Dist: flake8>=5.0.0; extra == "dev"
Requires-Dist: mypy>=0.990; extra == "dev"
Provides-Extra: interactive
Requires-Dist: plotly>=5.0.0; extra == "interactive"
Requires-Dist: jupyter>=1.0.0; extra == "interactive"
Requires-Dist: ipywidgets>=7.6.0; extra == "interactive"
Dynamic: author
Dynamic: home-page
Dynamic: license-file
Dynamic: requires-python
